trie/TrieNode.py
trie/__init__.py
trie/main.py
triefunc-0.0.1.dist-info/METADATA
triefunc-0.0.1.dist-info/WHEEL
triefunc-0.0.1.dist-info/top_level.txt
triefunc-0.0.1.dist-info/RECORD
